{
    "loot": [
        {
            "itemID": "305",
            "itemName": "Fair Saber",
            "DropChance": 5
        },
        {
            "itemID": "302",
            "itemName": "Fair Battle Axe",
            "DropChance": 5
        },
        {
            "itemID": "308",
            "itemName": "Fair Falchion",
            "DropChance": 5
        },
        {
            "itemID": "315",
            "itemName": "Fair Heavy Mace",
            "DropChance": 5
        },
        {
            "itemID": "311",
            "itemName": "Fair Halberd",
            "DropChance": 5
        },
        {
            "itemID": "105",
            "itemName": "Fair Gambeson Robes",
            "DropChance": 5
        },
        {
            "itemID": "102",
            "itemName": "Fair Elk Hide Armor",
            "DropChance": 5
        },
        {
            "itemID": "108",
            "itemName": "Fair Hauberk",
            "DropChance": 5
        },
        {
            "itemID": "114",
            "itemName": "Fair Plackart",
            "DropChance": 5
        },
        {
            "itemID": "111",
            "itemName": "Fair Laminar Plate Mail",
            "DropChance": 5
        },     
        {
            "itemID": "306",
            "itemName": "Excellent Saber",
            "DropChance": 3
        },
        {
            "itemID": "303",
            "itemName": "Excellent Battle Axe",
            "DropChance": 3
        },
        {
            "itemID": "309",
            "itemName": "Excellent Falchion",
            "DropChance": 3
        },
        {
            "itemID": "314",
            "itemName": "Excellent Heavy Mace",
            "DropChance": 3
        },
        {
            "itemID": "312",
            "itemName": "Excellent Halberd",
            "DropChance": 3
        },
        {
            "itemID": "106",
            "itemName": "Excellent Gambeson Robes",
            "DropChance": 3
        },
        {
            "itemID": "103",
            "itemName": "Excellent Elk Hide Armor",
            "DropChance": 3
        },
        {
            "itemID": "109",
            "itemName": "Excellent Hauberk",
            "DropChance": 3
        },
        {
            "itemID": "115",
            "itemName": "Excellent Plackart",
            "DropChance": 3
        },
        {
            "itemID": "112",
            "itemName": "Excellent Laminar Plate Mail",
            "DropChance": 3
        },
        {
            "itemID": "501",
            "itemName": "Elixir of Health",
            "DropChance": 4
        },
        {
            "itemID": "505",
            "itemName": "Vial of Pure Strength",
            "DropChance": 1
        },
        {
            "itemID": "504",
            "itemName": "Vial of Pure Speed",
            "DropChance": 1
        },
        {
            "itemID": "502",
            "itemName": "Vial of Pure Adrenaline",
            "DropChance": 1
        },
        {
            "itemID": "503",
            "itemName": "Vial of Pure Stamina",
            "DropChance": 3
        },
        {
            "itemID": "700",
            "itemName": "Ancient Vase",
            "DropChance": 2
        },
        {
            "itemID": "702",
            "itemName": "Golden Chalice",
            "DropChance": 2
        },        {
            "itemID": "708",
            "itemName": "Obsidian Staff",
            "DropChance": 1
        },        {
            "itemID": "709",
            "itemName": "Engraved Locket",
            "DropChance": 2
        },        {
            "itemID": "713",
            "itemName": "Carved Bone Totem",
            "DropChance": 2
        },        {
            "itemID": "716",
            "itemName": "Shrunken Head",
            "DropChance": 1
        }
    ]
}
